<?xml version="1.0"?>
<Configuration xmlns:xsi="http://www.w3.org/2001/XMLSchema-instance" xmlns:xsd="http://www.w3.org/2001/XMLSchema">
  <ThetaSafe>-28</ThetaSafe>
  <ThetaCamStart>5.98</ThetaCamStart>
  <ZCamTableRange>250</ZCamTableRange>
  <ZCamTableOffset>1.792</ZCamTableOffset>
  <CamTableStep128FuncOfZ>2954</CamTableStep128FuncOfZ>
  <ZCamTjerkMin>25</ZCamTjerkMin>
  <ZCamAccel>1000</ZCamAccel>
  <GripOpenDelta>10</GripOpenDelta>
  <TCamX>2</TCamX>
  <ArmLength>250</ArmLength>
  <MaxY>249.9</MaxY>
  <FingerOffsetZ>0</FingerOffsetZ>
  <PlateOffsetZ>0</PlateOffsetZ>
  <ParkPositionX>-500</ParkPositionX>
  <ParkPositionZ>0</ParkPositionZ>
  <ForceRehome>false</ForceRehome>
  <MinimumAllowableToolZHeightForPVT>-264</MinimumAllowableToolZHeightForPVT>
  <BarcodeMisreadThreshold>4</BarcodeMisreadThreshold>
  <RackConfigurations>
    <RackConfig>
      <RackNumber>1</RackNumber>
      <DefaultPlateType>Barcode</DefaultPlateType>
      <Slots>
        <Slot>
          <SlotNumber>7</SlotNumber>
          <PlateType>Tipbox</PlateType>
        </Slot>
        <Slot>
          <SlotNumber>8</SlotNumber>
          <PlateType>Tipbox</PlateType>
        </Slot>
      </Slots>
    </RackConfig>
    <RackConfig>
      <RackNumber>2</RackNumber>
      <DefaultPlateType>Barcode</DefaultPlateType>
    </RackConfig>
    <RackConfig>
      <RackNumber>3</RackNumber>
      <DefaultPlateType>Barcode</DefaultPlateType>
    </RackConfig>
    <RackConfig>
      <RackNumber>4</RackNumber>
      <DefaultPlateType>Barcode</DefaultPlateType>
    </RackConfig>
    <RackConfig>
      <RackNumber>5</RackNumber>
      <DefaultPlateType>Barcode</DefaultPlateType>
    </RackConfig>
  </RackConfigurations>
  <TeachpointServicePort>2345</TeachpointServicePort>
</Configuration>